dezero/__init__.py
dezero/core.py
dezero/core_simple.py
dezero/cuda.py
dezero/dataloaders.py
dezero/datasets.py
dezero/functions.py
dezero/functions_conv.py
dezero/layers.py
dezero/models.py
dezero/optimizers.py
dezero/transforms.py
dezero/utils.py
dezero-0.0.13.dist-info/LICENSE.md
dezero-0.0.13.dist-info/METADATA
dezero-0.0.13.dist-info/WHEEL
dezero-0.0.13.dist-info/top_level.txt
dezero-0.0.13.dist-info/RECORD
