Metadata-Version: 1.0
Name: dezero
Version: 0.0.13
Summary: Deep Learning Framework from Zero
Home-page: UNKNOWN
Author: Koki Saitoh
Author-email: koki0702@gmail.com
License: MIT License
Platform: UNKNOWN
